koreanize_matplotlib/__init__.py
koreanize_matplotlib/koreanize_matplotlib.py
koreanize_matplotlib/fonts/NanumGothic.ttf
koreanize_matplotlib/fonts/NanumGothicBold.ttf
koreanize_matplotlib/fonts/NanumGothicExtraBold.ttf
koreanize_matplotlib/fonts/NanumGothicLight.ttf
koreanize_matplotlib-0.1.0.dist-info/LICENSE
koreanize_matplotlib-0.1.0.dist-info/METADATA
koreanize_matplotlib-0.1.0.dist-info/WHEEL
koreanize_matplotlib-0.1.0.dist-info/top_level.txt
koreanize_matplotlib-0.1.0.dist-info/RECORD
