Metadata-Version: 2.1
Name: koreanize-matplotlib
Version: 0.1.0
Summary: matplotlib의 폰트 설정을 자동으로 한국어화
Home-page: https://github.com/ychoi-kr/koreanize-matplotlib
Author: ychoi-kr
Author-email: ychoi_kr@naever.com
License: MIT License
Platform: UNKNOWN
License-File: LICENSE
Requires-Dist: matplotlib
